{
  "page_number": 163,
  "output_name": "cropped_nethack_uncropped_both_sides_ordered-157.png",
  "source_filename": "pdf163__nethack_uncropped_both_sides_ordered-157.png",
  "split": null,
  "mode": "body",
  "target_size": [
    1700,
    2440
  ],
  "source_size": [
    2550,
    4200
  ],
  "output_size": [
    1700,
    2440
  ],
  "angle_projection": 0.48,
  "angle_hough": 0.0,
  "angle_line": 0.436253849900454,
  "angle_used": 0.436253849900454,
  "projection_peak_z": 0.7516557078187565,
  "projection_second_gap": 0.0289764404296875,
  "projection_hough_delta": 0.48,
  "hough_confidence": 1.2,
  "line_confidence": 3.8712806119025682,
  "line_segment_count": 13,
  "foreground_component_count": 1021,
  "content_bbox": [
    589,
    192,
    2089,
    2309
  ],
  "expanded_bbox": [
    494,
    97,
    2184,
    2444
  ],
  "crop_window": [
    430,
    0,
    2130,
    2440
  ],
  "trim_insets": [
    52,
    0,
    36,
    72
  ],
  "page_side": "right",
  "inner_edge": "left",
  "outer_edge": "right",
  "book_page_number": 163,
  "reference_match_score": 0.8768763542175293,
  "scanner_tail_detected": true,
  "scanner_tail_confidence": 3.534293889463357,
  "content_area_ratio": 0.2964985994397759,
  "min_crop_margin": 41,
  "padding_px": 0,
  "flags": [
    "projection_hough_disagree",
    "reference_crop",
    "reference_trim",
    "scanner_tail_detected",
    "used_line_angle"
  ],
  "paths": {
    "color": "work/processed-refined/color/cropped_nethack_uncropped_both_sides_ordered-157.png",
    "gray_for_ocr": "work/processed-refined/gray_for_ocr/cropped_nethack_uncropped_both_sides_ordered-157.png",
    "debug": "work/processed-refined/debug/cropped_nethack_uncropped_both_sides_ordered-157.png"
  }
}
